python_accelerate/__init__.py
python_accelerate/data_science/__init__.py
python_accelerate/data_science/utils.py
python_accelerate/http/__init__.py
python_accelerate/visualize/__init__.py
python_accelerate/visualize/seaborn/__init__.py
python_accelerate-0.0.5.dist-info/LICENSE.txt
python_accelerate-0.0.5.dist-info/METADATA
python_accelerate-0.0.5.dist-info/WHEEL
python_accelerate-0.0.5.dist-info/top_level.txt
python_accelerate-0.0.5.dist-info/RECORD
