Metadata-Version: 2.1
Name: python-accelerate
Version: 0.0.5
Summary: All-around utility functions for the Python programmer.
Download-URL: https://pypi.python.org/pypi/python-accelerate
Author: Mathew Stylianidis
Maintainer: Mathew Stylianidis
License: MIT License
Project-URL: Bug Tracker, https://github.com/MathewStylianidis/python-accelerate/issues
Project-URL: Source Code, https://github.com/MathewStylianidis/python-accelerate
Classifier: Programming Language :: Python :: 3.9
Classifier: License :: OSI Approved :: MIT License
Classifier: Operating System :: OS Independent
Requires-Python: >=3.9
License-File: LICENSE.txt
